[
  {
    "index": 0,
    "text": "DAFTAR SUPPLIER & BAHAN BAKU TOKO SEJAHTERA",
    "score": 0.9491417407989502,
    "box": [
      [
        220.0,
        398.0
      ],
      [
        1050.0,
        384.0
      ],
      [
        1051.0,
        419.0
      ],
      [
        220.0,
        434.0
      ]
    ]
  },
  {
    "index": 1,
    "text": "No",
    "score": 0.9831947088241577,
    "box": [
      [
        151.0,
        571.0
      ],
      [
        191.0,
        571.0
      ],
      [
        191.0,
        603.0
      ],
      [
        151.0,
        603.0
      ]
    ]
  },
  {
    "index": 2,
    "text": "Nama Supplier",
    "score": 0.9675922989845276,
    "box": [
      [
        235.0,
        570.0
      ],
      [
        433.0,
        570.0
      ],
      [
        433.0,
        605.0
      ],
      [
        235.0,
        605.0
      ]
    ]
  },
  {
    "index": 3,
    "text": "Bahan Baku",
    "score": 0.9614545702934265,
    "box": [
      [
        567.0,
        568.0
      ],
      [
        736.0,
        568.0
      ],
      [
        736.0,
        600.0
      ],
      [
        567.0,
        600.0
      ]
    ]
  },
  {
    "index": 4,
    "text": "Harga(Rp)",
    "score": 0.9255375266075134,
    "box": [
      [
        838.0,
        562.0
      ],
      [
        982.0,
        562.0
      ],
      [
        982.0,
        600.0
      ],
      [
        838.0,
        600.0
      ]
    ]
  },
  {
    "index": 5,
    "text": "Kontak",
    "score": 0.9974247813224792,
    "box": [
      [
        1013.0,
        562.0
      ],
      [
        1113.0,
        568.0
      ],
      [
        1111.0,
        602.0
      ],
      [
        1010.0,
        596.0
      ]
    ]
  },
  {
    "index": 6,
    "text": "1",
    "score": 0.9937366247177124,
    "box": [
      [
        149.0,
        616.0
      ],
      [
        182.0,
        616.0
      ],
      [
        182.0,
        650.0
      ],
      [
        149.0,
        650.0
      ]
    ]
  },
  {
    "index": 7,
    "text": "Beras 25kg",
    "score": 0.9605635404586792,
    "box": [
      [
        522.0,
        610.0
      ],
      [
        684.0,
        614.0
      ],
      [
        683.0,
        652.0
      ],
      [
        521.0,
        648.0
      ]
    ]
  },
  {
    "index": 8,
    "text": "300.000",
    "score": 0.9963951110839844,
    "box": [
      [
        855.0,
        611.0
      ],
      [
        976.0,
        611.0
      ],
      [
        976.0,
        643.0
      ],
      [
        855.0,
        643.0
      ]
    ]
  },
  {
    "index": 9,
    "text": "0812-xxxx",
    "score": 0.9479020237922668,
    "box": [
      [
        999.0,
        607.0
      ],
      [
        1137.0,
        613.0
      ],
      [
        1135.0,
        649.0
      ],
      [
        998.0,
        642.0
      ]
    ]
  },
  {
    "index": 10,
    "text": "Toko Tani Makmur",
    "score": 0.969774067401886,
    "box": [
      [
        218.0,
        618.0
      ],
      [
        462.0,
        618.0
      ],
      [
        462.0,
        648.0
      ],
      [
        218.0,
        648.0
      ]
    ]
  },
  {
    "index": 11,
    "text": "2",
    "score": 0.9960779547691345,
    "box": [
      [
        149.0,
        657.0
      ],
      [
        180.0,
        657.0
      ],
      [
        180.0,
        695.0
      ],
      [
        149.0,
        695.0
      ]
    ]
  },
  {
    "index": 12,
    "text": "Sumber Telur Jaya",
    "score": 0.9490159153938293,
    "box": [
      [
        210.0,
        655.0
      ],
      [
        462.0,
        661.0
      ],
      [
        461.0,
        697.0
      ],
      [
        209.0,
        691.0
      ]
    ]
  },
  {
    "index": 13,
    "text": "Telur Ayam 1 Peti",
    "score": 0.9568790197372437,
    "box": [
      [
        522.0,
        659.0
      ],
      [
        765.0,
        655.0
      ],
      [
        766.0,
        693.0
      ],
      [
        522.0,
        697.0
      ]
    ]
  },
  {
    "index": 14,
    "text": "450.000",
    "score": 0.9946630597114563,
    "box": [
      [
        856.0,
        655.0
      ],
      [
        976.0,
        655.0
      ],
      [
        976.0,
        687.0
      ],
      [
        856.0,
        687.0
      ]
    ]
  },
  {
    "index": 15,
    "text": "0857-xxxx",
    "score": 0.9279434680938721,
    "box": [
      [
        999.0,
        651.0
      ],
      [
        1144.0,
        658.0
      ],
      [
        1143.0,
        693.0
      ],
      [
        998.0,
        687.0
      ]
    ]
  },
  {
    "index": 16,
    "text": "3",
    "score": 0.9988247752189636,
    "box": [
      [
        149.0,
        702.0
      ],
      [
        180.0,
        702.0
      ],
      [
        180.0,
        737.0
      ],
      [
        149.0,
        737.0
      ]
    ]
  },
  {
    "index": 17,
    "text": "PT.Minyak Nusantara",
    "score": 0.9603348970413208,
    "box": [
      [
        210.0,
        700.0
      ],
      [
        502.0,
        705.0
      ],
      [
        501.0,
        741.0
      ],
      [
        209.0,
        735.0
      ]
    ]
  },
  {
    "index": 18,
    "text": "Minyak Goreng 1 Dus",
    "score": 0.9691404104232788,
    "box": [
      [
        524.0,
        703.0
      ],
      [
        816.0,
        703.0
      ],
      [
        816.0,
        739.0
      ],
      [
        524.0,
        739.0
      ]
    ]
  },
  {
    "index": 19,
    "text": "240.000",
    "score": 0.9960742592811584,
    "box": [
      [
        856.0,
        702.0
      ],
      [
        978.0,
        702.0
      ],
      [
        978.0,
        734.0
      ],
      [
        856.0,
        734.0
      ]
    ]
  },
  {
    "index": 20,
    "text": "0821-xxxx",
    "score": 0.8895902633666992,
    "box": [
      [
        1003.0,
        698.0
      ],
      [
        1144.0,
        706.0
      ],
      [
        1142.0,
        738.0
      ],
      [
        1001.0,
        730.0
      ]
    ]
  },
  {
    "index": 21,
    "text": "4",
    "score": 0.9981259703636169,
    "box": [
      [
        149.0,
        746.0
      ],
      [
        178.0,
        746.0
      ],
      [
        178.0,
        782.0
      ],
      [
        149.0,
        782.0
      ]
    ]
  },
  {
    "index": 22,
    "text": "Gula Merah Sari",
    "score": 0.9438923001289368,
    "box": [
      [
        211.0,
        746.0
      ],
      [
        435.0,
        750.0
      ],
      [
        434.0,
        782.0
      ],
      [
        211.0,
        778.0
      ]
    ]
  },
  {
    "index": 23,
    "text": "Minyak Goreng 1 Dus",
    "score": 0.9749487042427063,
    "box": [
      [
        522.0,
        748.0
      ],
      [
        816.0,
        746.0
      ],
      [
        816.0,
        782.0
      ],
      [
        522.0,
        784.0
      ]
    ]
  },
  {
    "index": 24,
    "text": "240.000",
    "score": 0.9952284097671509,
    "box": [
      [
        856.0,
        746.0
      ],
      [
        978.0,
        746.0
      ],
      [
        978.0,
        778.0
      ],
      [
        856.0,
        778.0
      ]
    ]
  },
  {
    "index": 25,
    "text": "0821-xxxx",
    "score": 0.8462947607040405,
    "box": [
      [
        1005.0,
        744.0
      ],
      [
        1146.0,
        750.0
      ],
      [
        1144.0,
        782.0
      ],
      [
        1003.0,
        776.0
      ]
    ]
  },
  {
    "index": 26,
    "text": "4",
    "score": 0.9981632828712463,
    "box": [
      [
        144.0,
        789.0
      ],
      [
        173.0,
        784.0
      ],
      [
        179.0,
        820.0
      ],
      [
        150.0,
        825.0
      ]
    ]
  },
  {
    "index": 27,
    "text": "Gula Merah Sari",
    "score": 0.9738336801528931,
    "box": [
      [
        207.0,
        793.0
      ],
      [
        436.0,
        793.0
      ],
      [
        436.0,
        828.0
      ],
      [
        207.0,
        828.0
      ]
    ]
  },
  {
    "index": 28,
    "text": "Gula Aren 1kg",
    "score": 0.973236083984375,
    "box": [
      [
        517.0,
        785.0
      ],
      [
        722.0,
        791.0
      ],
      [
        721.0,
        834.0
      ],
      [
        516.0,
        828.0
      ]
    ]
  },
  {
    "index": 29,
    "text": "25.000",
    "score": 0.9965135455131531,
    "box": [
      [
        871.0,
        791.0
      ],
      [
        980.0,
        791.0
      ],
      [
        980.0,
        823.0
      ],
      [
        871.0,
        823.0
      ]
    ]
  },
  {
    "index": 30,
    "text": "0819-xxxx",
    "score": 0.9138238430023193,
    "box": [
      [
        1002.0,
        785.0
      ],
      [
        1148.0,
        793.0
      ],
      [
        1146.0,
        831.0
      ],
      [
        999.0,
        822.0
      ]
    ]
  }
]